Metadata-Version: 1.0
Name: datadog-metrics
Version: 0.0.0
Summary: A tool for generating code from templates
Home-page: UNKNOWN
Author: UNKNOWN
Author-email: UNKNOWN
License: UNKNOWN
Platform: UNKNOWN
